torch_model_inspector-0.1.2.dist-info/licenses/LICENSE
torchinspect/__init__.py
torchinspect/core.py
torch_model_inspector-0.1.2.dist-info/METADATA
torch_model_inspector-0.1.2.dist-info/WHEEL
torch_model_inspector-0.1.2.dist-info/top_level.txt
torch_model_inspector-0.1.2.dist-info/RECORD
