Metadata-Version: 2.4
Name: torch_model_inspector
Version: 0.1.2
Summary: Lightweight utilities for inspecting PyTorch model shapes.
Author-email: Paing Thukha <ptkakaeitoe@gmail.com>
License-Expression: MIT
Keywords: pytorch,model,debug,shapes
Classifier: Development Status :: 3 - Alpha
Classifier: Programming Language :: Python :: 3
Classifier: Programming Language :: Python :: 3 :: Only
Classifier: Programming Language :: Python :: 3.8
Classifier: Programming Language :: Python :: 3.9
Classifier: Programming Language :: Python :: 3.10
Classifier: Programming Language :: Python :: 3.11
Classifier: Programming Language :: Python :: 3.12
Requires-Python: >=3.8
License-File: LICENSE
Requires-Dist: torch
Dynamic: license-file
